TheWatcher/__init__.py
TheWatcher/alerts.py
TheWatcher/alerts_gui.py
TheWatcher/alerts_log.txt
TheWatcher/cli.py
TheWatcher/dashboard.py
TheWatcher/devices_gui.py
TheWatcher/filters.py
TheWatcher/logging_setup.py
TheWatcher/main.py
TheWatcher/main_gui.py
TheWatcher/monitor_state.py
TheWatcher/monitoring_core.py
TheWatcher/network_monitoring.db
TheWatcher/network_scanner.py
TheWatcher/packet_processing.py
TheWatcher/packets_gui.py
TheWatcher/real_time_monitor.py
TheWatcher/retrieve_logs.py
TheWatcher/settings_gui.py
TheWatcher/setup.py
TheWatcher/traffic_log.txt
TheWatcher/traffic_summary.py
TheWatcher/utils.py
TheWatcher/__pycache__/alerts.cpython-312.pyc
TheWatcher/__pycache__/alerts_gui.cpython-312.pyc
TheWatcher/__pycache__/dashboard.cpython-312.pyc
TheWatcher/__pycache__/devices_gui.cpython-312.pyc
TheWatcher/__pycache__/filters.cpython-312.pyc
TheWatcher/__pycache__/logging_setup.cpython-312.pyc
TheWatcher/__pycache__/login.cpython-312.pyc
TheWatcher/__pycache__/main_gui.cpython-312.pyc
TheWatcher/__pycache__/monitor_state.cpython-312.pyc
TheWatcher/__pycache__/monitoring_core.cpython-312.pyc
TheWatcher/__pycache__/network_scanner.cpython-312.pyc
TheWatcher/__pycache__/packet_processing.cpython-312.pyc
TheWatcher/__pycache__/packets_gui.cpython-312.pyc
TheWatcher/__pycache__/real_time_monitor.cpython-312.pyc
TheWatcher/__pycache__/retrieve_logs.cpython-312.pyc
TheWatcher/__pycache__/settings_gui.cpython-312.pyc
TheWatcher/__pycache__/traffic_summary.cpython-312.pyc
TheWatcher/database/__init__.py
TheWatcher/database/database.py
TheWatcher/database/__pycache__/__init__.cpython-312.pyc
TheWatcher/database/__pycache__/database.cpython-312.pyc
thewatcher-0.1.0.dist-info/licenses/LICENSE
thewatcher-0.1.0.dist-info/METADATA
thewatcher-0.1.0.dist-info/WHEEL
thewatcher-0.1.0.dist-info/entry_points.txt
thewatcher-0.1.0.dist-info/top_level.txt
thewatcher-0.1.0.dist-info/RECORD
