Metadata-Version: 2.4
Name: TheWatcher
Version: 0.1.0
Summary: A simple network monitoring tool.
Home-page: https://github.com/Bigst3pp3r/Simple-Network-Monitoring-System-main
Author: Bigst3pp3r
Author-email: mltnkarani@gmail.com
Classifier: Programming Language :: Python :: 3
Classifier: Operating System :: OS Independent
Requires-Python: >=3.7
License-File: LICENSE
Requires-Dist: customtkinter
Requires-Dist: pyshark
Requires-Dist: matplotlib
Requires-Dist: scapy
Dynamic: license-file
